{
  "branches": {
    "AIML": {
      "name": "Artificial Intelligence & Machine Learning",
      "semesters": {
        "semester_1": {
          "name": "Semester 1",
          "year": 1,
          "subjects": [
            {
              "name": "Programming In 'C'",
              "faculty": "Rachna Sharma",
              "icon": "https://img.icons8.com/pulsar-line/96/code.png",
              "code": "ES-101",
              "credits": 3
            },
            {
              "name": "Applied Mathematics I",
              "faculty": "Mr. Devesh Kumar",
              "icon": "https://img.icons8.com/pulsar-line/96/tangent.png",
              "code": "BS-111",
              "credits": 4
            },
            {
              "name": "Applied Physics",
              "faculty": "Dr. Ajay Pal Indolia",
              "icon": "https://img.icons8.com/pulsar-line/96/physics.png",
              "code": "BS-105",
              "credits": 3
            },
            {
              "name": "Introduction to AI",
              "faculty": "Dr. Preeti Raj Verma",
              "icon": "https://img.icons8.com/pastel-glyph/64/intelligent-person.png",
              "code": "AI-101",
              "credits": 4
            },
            {
              "name": "Communication Skills",
              "faculty": "Dr. Meghna Sharma",
              "icon": "https://img.icons8.com/pulsar-line/96/talk-male.png",
              "code": "BS-113",
              "credits": 3
            }
          ]
        },
        "semester_2": {
          "name": "Semester 2",
          "year": 1,
          "subjects": [
            {
              "name": "Object Oriented Programming",
              "faculty": "Mr. Vikash Pandey",
              "icon": "https://img.icons8.com/ios/100/add-node.png",
              "code": "CS-102",
              "credits": 4
            },
            {
              "name": "Mathematics II",
              "faculty": "Dr. Rajesh Kumar",
              "icon": "https://img.icons8.com/pulsar-line/96/tangent.png",
              "code": "MATH-102",
              "credits": 4
            },
            {
              "name": "Data Structures Fundamentals",
              "faculty": "Ms. Upasna Joshi",
              "icon": "https://img.icons8.com/ios/100/add-node.png",
              "code": "DS-201",
              "credits": 4
            },
            {
              "name": "Linear Algebra for AI",
              "faculty": "Dr. Rajesh Kumar",
              "icon": "https://img.icons8.com/pulsar-line/96/tangent.png",
              "code": "AI-201",
              "credits": 3
            }
          ]
        }
      }
    },
    "AIDS": {
      "name": "Artificial Intelligence & Data Science",
      "semesters": {
        "semester_1": {
          "name": "Semester 1",
          "year": 1,
          "subjects": [
            {
              "name": "Programming In 'C'",
              "faculty": "Rachna Sharma",
              "icon": "https://img.icons8.com/pulsar-line/96/code.png",
              "code": "ES-101",
              "credits": 3
            },
            {
              "name": "Applied Mathematics I",
              "faculty": "Mr. Devesh Kumar",
              "icon": "https://img.icons8.com/pulsar-line/96/tangent.png",
              "code": "BS-111",
              "credits": 4
            },
            {
              "name": "Statistics & Probability",
              "faculty": "Dr. Rajesh Kumar",
              "icon": "https://img.icons8.com/pulsar-line/96/statistics.png",
              "code": "STAT-101",
              "credits": 3
            },
            {
              "name": "Introduction to Data Science",
              "faculty": "Ms. Maroof",
              "icon": "https://img.icons8.com/pulsar-line/96/database.png",
              "code": "DS-101",
              "credits": 4
            },
            {
              "name": "Communication Skills",
              "faculty": "Dr. Meghna Sharma",
              "icon": "https://img.icons8.com/pulsar-line/96/talk-male.png",
              "code": "BS-113",
              "credits": 3
            }
          ]
        }
      }
    },
    "CST": {
      "name": "Computer Science & Technology",
      "semesters": {
        "semester_1": {
          "name": "Semester 1",
          "year": 1,
          "subjects": [
            {
              "name": "Programming In 'C'",
              "faculty": "Rachna Sharma",
              "icon": "https://img.icons8.com/pulsar-line/96/code.png",
              "code": "ES-101",
              "credits": 3
            },
            {
              "name": "Applied Mathematics I",
              "faculty": "Mr. Devesh Kumar",
              "icon": "https://img.icons8.com/pulsar-line/96/tangent.png",
              "code": "BS-111",
              "credits": 4
            },
            {
              "name": "Digital Electronics",
              "faculty": "Dr. Mohan Lal",
              "icon": "https://img.icons8.com/pulsar-line/96/binary-file.png",
              "code": "ECE-101",
              "credits": 3
            },
            {
              "name": "Computer Fundamentals",
              "faculty": "Mr. Anuj Rajput",
              "icon": "https://img.icons8.com/pulsar-line/96/computer.png",
              "code": "CST-101",
              "credits": 4
            },
            {
              "name": "Communication Skills",
              "faculty": "Dr. Meghna Sharma",
              "icon": "https://img.icons8.com/pulsar-line/96/talk-male.png",
              "code": "BS-113",
              "credits": 3
            }
          ]
        }
      }
    },
    "CSE": {
      "name": "Computer Science & Engineering",
      "semesters": {
        "semester_1": {
          "name": "Semester 1",
          "year": 1,
          "subjects": [
            {
              "name": "Programming In 'C'",
              "faculty": "Rachna Sharma",
              "icon": "https://img.icons8.com/pulsar-line/96/code.png",
              "code": "ES-101 / ES-102",
              "credits": 3
            },
            {
              "name": "Applied Chemistry",
              "faculty": "Dr. Neeta Pandey",
              "icon": "https://img.icons8.com/pulsar-line/96/acid-flask.png",
              "code": "BS-103 / BS-104",
              "credits": 3
            },
            {
              "name": "Applied Physics",
              "faculty": "Dr. Ajay Pal Indolia",
              "icon": "https://img.icons8.com/pulsar-line/96/physics.png",
              "code": "BS-105",
              "credits": 3
            },
            {
              "name": "Electrical Science",
              "faculty": "Ms. Satyaveer Gupt",
              "icon": "https://img.icons8.com/pulsar-line/96/electrical.png",
              "code": "CS101",
              "credits": 3
            },
            {
              "name": "Environmental Science",
              "faculty": "Dr. Alka Shrivastava",
              "icon": "https://img.icons8.com/pastel-glyph/64/hand-planting.png",
              "code": "ENG101",
              "credits": 3
            },
            {
              "name": "Applied Mathematics I",
              "faculty": "Mr. Devesh Kumar",
              "icon": "https://img.icons8.com/pulsar-line/96/tangent.png",
              "code": "BS-111",
              "credits": 4
            },
            {
              "name": "Communication Skills",
              "faculty": "Dr. Meghna Sharma",
              "icon": "https://img.icons8.com/pulsar-line/96/talk-male.png",
              "code": "BS-113 / BS-114",
              "credits": 3
            },
            {
              "name": "Indian Constitution",
              "faculty": "DG Sir",
              "icon": "https://img.icons8.com/pulsar-line/96/law.png",
              "code": "BS-113 / BS-114",
              "credits": 2
            },
            {
              "name": "Human Values and Ethics",
              "faculty": "Dr. Meghna Sharma",
              "icon": "https://img.icons8.com/pulsar-line/96/human-resources.png",
              "code": "BS-113 / BS-114",
              "credits": 2
            },
            {
              "name": "Manufacturing Processes",
              "faculty": "Rakesh Dhaka",
              "icon": "https://img.icons8.com/pulsar-line/96/services.png",
              "code": "BS-113 / BS-114",
              "credits": 2
            }
          ]
        }
      }
    },
    "semester_2": {
      "name": "Semester 2",
      "year": 1,
      "subjects": [
        {
          "name": "Mathematics II",
          "faculty": "Dr. Rajesh Kumar",
          "icon": "https://img.icons8.com/pulsar-line/96/tangent.png",
          "code": "MATH102",
          "credits": 4
        },
        {
          "name": "Physics II",
          "faculty": "Dr. Priya Sharma",
          "icon": "https://img.icons8.com/pulsar-line/96/physics.png",
          "code": "PHY102",
          "credits": 4
        },
        {
          "name": "Object Oriented Programming",
          "faculty": "Mr. Vikash Pandey",
          "icon": "https://img.icons8.com/ios/100/add-node.png",
          "code": "CS102",
          "credits": 4
        },
        {
          "name": "Digital Electronics",
          "faculty": "Dr. Mohan Lal",
          "icon": "https://img.icons8.com/pulsar-line/96/binary-file.png",
          "code": "ECE101",
          "credits": 3
        },
        {
          "name": "Engineering Graphics",
          "faculty": "Mr. Suresh Yadav",
          "icon": "https://img.icons8.com/pulsar-line/96/3d-modeling.png",
          "code": "ME101",
          "credits": 2
        }
      ]
    },
    "semester_3": {
      "name": "Semester 3",
      "year": 2,
      "subjects": [
        {
          "name": "Principle of AI",
          "faculty": "Preeti Raj Verma",
          "icon": "https://img.icons8.com/pastel-glyph/64/intelligent-person.png",
          "code": "AI301",
          "credits": 4
        },
        {
          "name": "Digital Logic Design",
          "faculty": "Mr. Anuj Rajput",
          "icon": "https://img.icons8.com/pulsar-line/96/binary-file.png",
          "code": "DLD301",
          "credits": 3
        },
        {
          "name": "Data Structures",
          "faculty": "Ms. Upasna Joshi",
          "icon": "https://img.icons8.com/ios/100/add-node.png",
          "code": "DSA301",
          "credits": 4
        },
        {
          "name": "PSLA",
          "faculty": "Mr. Padmesh",
          "icon": "https://img.icons8.com/pulsar-line/96/dice.png",
          "code": "PSLA301",
          "credits": 3
        },
        {
          "name": "Foundation of DS",
          "faculty": "Ms. Maroof",
          "icon": "https://img.icons8.com/pulsar-line/96/database.png",
          "code": "FDS301",
          "credits": 4
        },
        {
          "name": "UHV",
          "faculty": "Ms. Jyoti",
          "icon": "https://img.icons8.com/pulsar-line/96/volunteering.png",
          "code": "UHV301",
          "credits": 2
        },
        {
          "name": "Critical Reasoning",
          "faculty": "Ms. Upasna Joshi",
          "icon": "https://img.icons8.com/ios/100/persuasion-skills.png",
          "code": "CR301",
          "credits": 2
        }
      ]
    },
    "semester_4": {
      "name": "Semester 4",
      "year": 2,
      "subjects": [
        {
          "name": "Machine Learning",
          "faculty": "Dr. Rahul Khanna",
          "icon": "https://img.icons8.com/pastel-glyph/64/intelligent-person.png",
          "code": "ML401",
          "credits": 4
        },
        {
          "name": "Computer Networks",
          "faculty": "Ms. Kavita Sharma",
          "icon": "https://img.icons8.com/pulsar-line/96/network.png",
          "code": "CN401",
          "credits": 4
        },
        {
          "name": "Database Management",
          "faculty": "Mr. Deepak Gupta",
          "icon": "https://img.icons8.com/pulsar-line/96/database.png",
          "code": "DBMS401",
          "credits": 4
        },
        {
          "name": "Operating Systems",
          "faculty": "Dr. Anjali Verma",
          "icon": "https://img.icons8.com/pulsar-line/96/binary-file.png",
          "code": "OS401",
          "credits": 4
        },
        {
          "name": "Software Engineering",
          "faculty": "Mr. Rohit Agarwal",
          "icon": "https://img.icons8.com/pulsar-line/96/code.png",
          "code": "SE401",
          "credits": 3
        },
        {
          "name": "Web Development",
          "faculty": "Ms. Pooja Singh",
          "icon": "https://img.icons8.com/pulsar-line/96/web.png",
          "code": "WEB401",
          "credits": 3
        }
      ]
    },
    "semester_5": {
      "name": "Semester 5",
      "year": 3,
      "subjects": [
        {
          "name": "Advanced AI",
          "faculty": "Dr. Sanjay Kulkarni",
          "icon": "https://img.icons8.com/pastel-glyph/64/intelligent-person.png",
          "code": "AAI501",
          "credits": 4
        },
        {
          "name": "Computer Graphics",
          "faculty": "Ms. Ritu Pandey",
          "icon": "https://img.icons8.com/pulsar-line/96/3d-modeling.png",
          "code": "CG501",
          "credits": 3
        },
        {
          "name": "Distributed Systems",
          "faculty": "Dr. Manoj Kumar",
          "icon": "https://img.icons8.com/pulsar-line/96/network.png",
          "code": "DS501",
          "credits": 4
        },
        {
          "name": "Information Security",
          "faculty": "Mr. Arjun Rao",
          "icon": "https://img.icons8.com/pulsar-line/96/security-lock.png",
          "code": "IS501",
          "credits": 3
        },
        {
          "name": "Mobile App Development",
          "faculty": "Ms. Shreya Jain",
          "icon": "https://img.icons8.com/pulsar-line/96/mobile-phone.png",
          "code": "MAD501",
          "credits": 3
        }
      ]
    },
    "semester_6": {
      "name": "Semester 6",
      "year": 3,
      "subjects": [
        {
          "name": "Deep Learning",
          "faculty": "Dr. Pradeep Singh",
          "icon": "https://img.icons8.com/pastel-glyph/64/intelligent-person.png",
          "code": "DL601",
          "credits": 4
        },
        {
          "name": "Cloud Computing",
          "faculty": "Ms. Megha Agarwal",
          "icon": "https://img.icons8.com/pulsar-line/96/cloud.png",
          "code": "CC601",
          "credits": 4
        },
        {
          "name": "Blockchain Technology",
          "faculty": "Mr. Vikram Joshi",
          "icon": "https://img.icons8.com/pulsar-line/96/blockchain.png",
          "code": "BC601",
          "credits": 3
        },
        {
          "name": "Project Management",
          "faculty": "Dr. Sunita Rani",
          "icon": "https://img.icons8.com/pulsar-line/96/management.png",
          "code": "PM601",
          "credits": 2
        },
        {
          "name": "Capstone Project",
          "faculty": "Multiple Faculty",
          "icon": "https://img.icons8.com/pulsar-line/96/project.png",
          "code": "CP601",
          "credits": 6
        }
      ]
    },
    "semester_7": {
      "name": "Semester 7",
      "year": 4,
      "subjects": [
        {
          "name": "Advanced Algorithms",
          "faculty": "Dr. Amit Sharma",
          "icon": "https://img.icons8.com/ios/100/add-node.png",
          "code": "AA701",
          "credits": 4
        },
        {
          "name": "Cyber Security",
          "faculty": "Ms. Priya Kumari",
          "icon": "https://img.icons8.com/pulsar-line/96/security-lock.png",
          "code": "CS701",
          "credits": 3
        },
        {
          "name": "IoT Systems",
          "faculty": "Dr. Rajesh Gupta",
          "icon": "https://img.icons8.com/pulsar-line/96/network.png",
          "code": "IOT701",
          "credits": 3
        },
        {
          "name": "Research Methodology",
          "faculty": "Prof. Sunita Rani",
          "icon": "https://img.icons8.com/pulsar-line/96/book.png",
          "code": "RM701",
          "credits": 2
        },
        {
          "name": "Major Project I",
          "faculty": "Multiple Faculty",
          "icon": "https://img.icons8.com/pulsar-line/96/project.png",
          "code": "MP701",
          "credits": 8
        }
      ]
    },
    "semester_8": {
      "name": "Semester 8",
      "year": 4,
      "subjects": [
        {
          "name": "Industry Internship",
          "faculty": "Industry Mentors",
          "icon": "https://img.icons8.com/pulsar-line/96/management.png",
          "code": "INT801",
          "credits": 10
        },
        {
          "name": "Major Project II",
          "faculty": "Multiple Faculty",
          "icon": "https://img.icons8.com/pulsar-line/96/project.png",
          "code": "MP801",
          "credits": 8
        },
        {
          "name": "Professional Ethics",
          "faculty": "Dr. Kavita Jain",
          "icon": "https://img.icons8.com/pulsar-line/96/volunteering.png",
          "code": "PE801",
          "credits": 2
        }
      ]
    }
  }
}